setup.py
predictions_210406/__init__.py
predictions_210406/predict.py
predictions_210406/predict_classif.py
predictions_210406/predict_regr.py
predictions_210406.egg-info/PKG-INFO
predictions_210406.egg-info/SOURCES.txt
predictions_210406.egg-info/dependency_links.txt
predictions_210406.egg-info/not-zip-safe
predictions_210406.egg-info/top_level.txt