Metadata-Version: 1.0
Name: predictions-210406
Version: 0.1
Summary: Prediction models for classification and regression
Home-page: UNKNOWN
Author: John Bunge
Author-email: myemail@somethingsomething.com
License: UNKNOWN
Platform: UNKNOWN
